{"v":3,"stories":{"example-developers--docs":{"id":"example-developers--docs","title":"Example/Developers","name":"Docs","importPath":"./src/stories/Developers.stories.mdx","storiesImports":[],"standalone":false,"kind":"Example/Developers","story":"Docs","parameters":{"__id":"example-developers--docs","docsOnly":true,"fileName":"./src/stories/Developers.stories.mdx"}},"example-introduction--docs":{"id":"example-introduction--docs","title":"Example/Introduction","name":"Docs","importPath":"./src/stories/Introduction.stories.mdx","storiesImports":[],"standalone":false,"kind":"Example/Introduction","story":"Docs","parameters":{"__id":"example-introduction--docs","docsOnly":true,"fileName":"./src/stories/Introduction.stories.mdx"}},"example-productcallout--docs":{"id":"example-productcallout--docs","title":"Example/ProductCallout","name":"Docs","importPath":"./src/stories/ProductCallout.stories.jsx","storiesImports":[],"standalone":false,"kind":"Example/ProductCallout","story":"Docs","parameters":{"__id":"example-productcallout--docs","docsOnly":true,"fileName":"./src/stories/ProductCallout.stories.jsx"}},"example-productcallout--primary":{"id":"example-productcallout--primary","title":"Example/ProductCallout","name":"Primary","importPath":"./src/stories/ProductCallout.stories.jsx","kind":"Example/ProductCallout","story":"Primary","parameters":{"__id":"example-productcallout--primary","docsOnly":false,"fileName":"./src/stories/ProductCallout.stories.jsx"}},"example-producticons--docs":{"id":"example-producticons--docs","title":"Example/ProductIcons","name":"Docs","importPath":"./src/stories/ProductIcons.stories.jsx","storiesImports":[],"standalone":false,"kind":"Example/ProductIcons","story":"Docs","parameters":{"__id":"example-producticons--docs","docsOnly":true,"fileName":"./src/stories/ProductIcons.stories.jsx"}},"example-producticons--primary":{"id":"example-producticons--primary","title":"Example/ProductIcons","name":"Primary","importPath":"./src/stories/ProductIcons.stories.jsx","kind":"Example/ProductIcons","story":"Primary","parameters":{"__id":"example-producticons--primary","docsOnly":false,"fileName":"./src/stories/ProductIcons.stories.jsx"}},"example-productjumbo--docs":{"id":"example-productjumbo--docs","title":"Example/ProductJumbo","name":"Docs","importPath":"./src/stories/ProductJumbo.stories.jsx","storiesImports":[],"standalone":false,"kind":"Example/ProductJumbo","story":"Docs","parameters":{"__id":"example-productjumbo--docs","docsOnly":true,"fileName":"./src/stories/ProductJumbo.stories.jsx"}},"example-productjumbo--primary":{"id":"example-productjumbo--primary","title":"Example/ProductJumbo","name":"Primary","importPath":"./src/stories/ProductJumbo.stories.jsx","kind":"Example/ProductJumbo","story":"Primary","parameters":{"__id":"example-productjumbo--primary","docsOnly":false,"fileName":"./src/stories/ProductJumbo.stories.jsx"}},"example-productlinks--docs":{"id":"example-productlinks--docs","title":"Example/ProductLinks","name":"Docs","importPath":"./src/stories/ProductLinks.stories.jsx","storiesImports":[],"standalone":false,"kind":"Example/ProductLinks","story":"Docs","parameters":{"__id":"example-productlinks--docs","docsOnly":true,"fileName":"./src/stories/ProductLinks.stories.jsx"}},"example-productlinks--primary":{"id":"example-productlinks--primary","title":"Example/ProductLinks","name":"Primary","importPath":"./src/stories/ProductLinks.stories.jsx","kind":"Example/ProductLinks","story":"Primary","parameters":{"__id":"example-productlinks--primary","docsOnly":false,"fileName":"./src/stories/ProductLinks.stories.jsx"}},"example-productquote--docs":{"id":"example-productquote--docs","title":"Example/ProductQuote","name":"Docs","importPath":"./src/stories/ProductQuote.stories.jsx","storiesImports":[],"standalone":false,"kind":"Example/ProductQuote","story":"Docs","parameters":{"__id":"example-productquote--docs","docsOnly":true,"fileName":"./src/stories/ProductQuote.stories.jsx"}},"example-productquote--primary":{"id":"example-productquote--primary","title":"Example/ProductQuote","name":"Primary","importPath":"./src/stories/ProductQuote.stories.jsx","kind":"Example/ProductQuote","story":"Primary","parameters":{"__id":"example-productquote--primary","docsOnly":false,"fileName":"./src/stories/ProductQuote.stories.jsx"}},"example-productquote--background-color":{"id":"example-productquote--background-color","title":"Example/ProductQuote","name":"Background Color","importPath":"./src/stories/ProductQuote.stories.jsx","kind":"Example/ProductQuote","story":"Background Color","parameters":{"__id":"example-productquote--background-color","docsOnly":false,"fileName":"./src/stories/ProductQuote.stories.jsx"}},"example-producttext--docs":{"id":"example-producttext--docs","title":"Example/ProductText","name":"Docs","importPath":"./src/stories/ProductText.stories.jsx","storiesImports":[],"standalone":false,"kind":"Example/ProductText","story":"Docs","parameters":{"__id":"example-producttext--docs","docsOnly":true,"fileName":"./src/stories/ProductText.stories.jsx"}},"example-producttext--primary":{"id":"example-producttext--primary","title":"Example/ProductText","name":"Primary","importPath":"./src/stories/ProductText.stories.jsx","kind":"Example/ProductText","story":"Primary","parameters":{"__id":"example-producttext--primary","docsOnly":false,"fileName":"./src/stories/ProductText.stories.jsx"}},"example-producttext--background-color":{"id":"example-producttext--background-color","title":"Example/ProductText","name":"Background Color","importPath":"./src/stories/ProductText.stories.jsx","kind":"Example/ProductText","story":"Background Color","parameters":{"__id":"example-producttext--background-color","docsOnly":false,"fileName":"./src/stories/ProductText.stories.jsx"}},"example-stickynav--docs":{"id":"example-stickynav--docs","title":"Example/Stickynav","name":"Docs","importPath":"./src/stories/Stickynav.stories.jsx","storiesImports":[],"standalone":false,"kind":"Example/Stickynav","story":"Docs","parameters":{"__id":"example-stickynav--docs","docsOnly":true,"fileName":"./src/stories/Stickynav.stories.jsx"}},"example-stickynav--primary":{"id":"example-stickynav--primary","title":"Example/Stickynav","name":"Primary","importPath":"./src/stories/Stickynav.stories.jsx","kind":"Example/Stickynav","story":"Primary","parameters":{"__id":"example-stickynav--primary","docsOnly":false,"fileName":"./src/stories/Stickynav.stories.jsx"}}}}
